tree_sitter_systemverilog/__init__.py
tree_sitter_systemverilog/__init__.pyi
tree_sitter_systemverilog/_binding.abi3.so
tree_sitter_systemverilog/binding.c
tree_sitter_systemverilog/py.typed
tree_sitter_systemverilog/queries/highlights.scm
tree_sitter_systemverilog-0.3.1.dist-info/METADATA
tree_sitter_systemverilog-0.3.1.dist-info/WHEEL
tree_sitter_systemverilog-0.3.1.dist-info/top_level.txt
tree_sitter_systemverilog-0.3.1.dist-info/RECORD
tree_sitter_systemverilog-0.3.1.dist-info/licenses/LICENSE
