Metadata-Version: 2.4
Name: tree-sitter-systemverilog
Version: 0.3.1
Summary: SystemVerilog 1800-2023 Parser
Author-email: "Gonzalo M. Larumbe" <gonzalomlarumbe@gmail.com>
License: MIT
Project-URL: Homepage, https://github.com/gmlarumbe/tree-sitter-systemverilog
Project-URL: Funding, https://github.com/sponsors/gmlarumbe
Keywords: incremental,parsing,tree-sitter,systemverilog
Classifier: Intended Audience :: Developers
Classifier: Topic :: Software Development :: Compilers
Classifier: Topic :: Text Processing :: Linguistic
Classifier: Typing :: Typed
Requires-Python: >=3.10
License-File: LICENSE
Provides-Extra: core
Requires-Dist: tree-sitter~=0.24; extra == "core"
Dynamic: license-file
